skeetpy.py
skeetpy-0.1.3.dist-info/LICENSE
skeetpy-0.1.3.dist-info/WHEEL
skeetpy-0.1.3.dist-info/METADATA
skeetpy-0.1.3.dist-info/RECORD
