Metadata-Version: 2.1
Name: skeetpy
Version: 0.1.3
Summary: Skeetpy is a Python library for interacting with the AT protocol.
Author-email: Yves Junqueira <yves.junqueira@gmail.com>
Classifier: License :: OSI Approved :: MIT License
Project-URL: Home, https://github.com/nictuku/skeetpy
